mocet/__init__.py
mocet/simulation.py
mocet/utils.py
mocet-0.0.9.dist-info/licenses/LICENSE
mocet-0.0.9.dist-info/METADATA
mocet-0.0.9.dist-info/WHEEL
mocet-0.0.9.dist-info/top_level.txt
mocet-0.0.9.dist-info/RECORD
