Metadata-Version: 2.4
Name: mocet
Version: 0.0.9
Summary: Python package for head-motion corrected eye-tracking
Home-page: https://github.com/jwparks/mocet
Author: Jiwoong Park
Author-email: Jiwoong Park <jiwoongpark@skku.edu>
Project-URL: Homepage, https://github.com/jwpark/mocet
Classifier: Programming Language :: Python :: 3
Classifier: License :: OSI Approved :: MIT License
Classifier: Operating System :: OS Independent
Requires-Python: >=3.10
License-File: LICENSE
Dynamic: author
Dynamic: home-page
Dynamic: license-file
Dynamic: requires-python
